{
  "id": "lai-c9a8de0f031a",
  "order": 91,
  "title": "不同高僧大德的示现是为了带给我们不一样的提醒",
  "quote": "你们知道宗萨仁波切怎么说门措上师吗？",
  "theme": "修行 · 情绪",
  "themes": [
    "修行",
    "情绪"
  ],
  "keywords": [
    "修行",
    "佛法",
    "菩萨",
    "解脱",
    "空性",
    "烦恼",
    "执着",
    "福报"
  ],
  "userConcerns": [
    "修行迷茫",
    "如何回到当下",
    "认识生命本质",
    "情绪反复",
    "内心烦恼",
    "焦虑与恐惧"
  ],
  "paragraphs": [
    "你们知道宗萨仁波切怎么说门措上师吗？他说：“门措上师是我渴望接受灌顶的上师，如果他现在就在这里，我会像一棵树一样倒下来，匍匐在空行母脚下接受灌顶。”",
    "还有一位叫顶果钦哲仁波切，这一位也非常值得大家去重视。顶果钦哲仁波切，你们看过他的作品、看过他讲的话，应该就能知道。",
    "但是我还是那句话：看看自己是不是一个合格的法器。自己要有出离心，要敢舍——不仅是舍名利情，更要勇敢去看穿自我的虚幻，要舍掉这个自我，你才能被大圆满直接接引的。",
    "那么，比如说我推荐顶果钦哲仁波切、邱阳创巴仁波切，你们才会更容易发现这些上师的圆满和究竟。",
    "当然不是说体佛法师、元音老人他们不够圆满——也很圆满，只不过说因为之前互联网不是不让讲西藏吗？",
    "今天讲的这几个都是西藏的、藏地那边的。有一位读者问过我，能不能推荐几个藏地那边的上师，所以就顺便说了。当然不止他们，虽然活佛没有大家想的那么多。",
    "为什么互联网会去封杀西藏的很多消息？也有原因。因为活佛这种东西是很神秘的，信仰对人的影响是非常吓人的。",
    "有一段时间，就是可能，有一些别有居心的组织在北京居然抛洒了两千多名活佛。不说全球吧，全中国他们散播了两千多名假的活佛，去招摇撞骗，去进行各种秘密的东西。",
    "那你说北京那边会允许这种事情发生吗？活佛没有那么多的，那肯定要大面积地去扼杀这种不良的趋势，是吧？而那些真正的上师、真正的活佛也必然会理解这样的行为。其实会有点影响，但影响不会特别大。",
    "其实我也不太会去跟大家推荐西藏那边的上师，因为那边骗子太多了。它已经变成商业化的很多行为了。",
    "一听活佛，多少人抢着去供养？有多少的所谓的打着这个修行的旗号，搞男女双修，把女性圈养为自己的情人，好多这样的。",
    "注意！性能量也是很好的能量。其实大家认为性能量先入为主、下定义认为是淫秽，就会排斥它、去定义它、去解读它怎么怎么样。",
    "能量就是能量，没有什么性能量、什么什么能量的很多分别。是能量用在这个地方、在这个区域，或者说以这样的频率在呈现着，被大家表达为什么性能量、什么什么能量。",
    "性能量是孕育生命的，一定有它很有用、很强大的一面。所以，很多的能量的修持的次第、修炼的方法，它会从能量上下手，它不是没有原因的。但是为什么这个东西不适合公开？你们可想而知了吗？",
    "第一，有那么多很有证量的上师吗？没有那么多。你走能量修行的路子，他没有办法一对多呀，对不对？",
    "首先上师都没那么多，好的上师没有那么多，真正很有证量的上师都没有那么多，那真正很有根器的学生也没那么容易遇到的。那是不是不能去公开这种东西？",
    "你公开的话，是不是一定会给更多的人性之恶更多机会？西藏就有这种局面的有很多。所以现在是真假活佛搞得，确实世人也失去信心，因为世人、众生他分不清，反正凡事都有原因的。",
    "所以我也不太愿意去跟大家聊藏地那边的事情，不仅是因为它涉及能量修持上面很隐秘、很有讲究，第二个就是隐秘的东西里面会隐藏着东西。",
    "还有一位叫邱阳创巴仁波切，刚刚已经说了。他是一位非常勇敢的、很不一般的行者。有些大修行人，他示现很不一般的相。",
    "比如他示现一些很荒诞怪异的相，他是有用处的，他有的时候是可以接引只差临门一脚的修行人的。因为行径不一般的大修行人，他可以帮助那些修行人破很多修行相，你懂我意思吗？",
    "就很简单，我举个例子吧。越厉害的师父，那种非常非常厉害的师父，你们一定是看不懂他的行径的。他没有任何限制，他完全对机说法、因材施教。",
    "比如他培养了他的一些弟子，他培养他的学生，当他的学生实践到一定地步的时候，需要破一些相的时候，这个师父可能会用各种不一般的、众生不一定能接纳的形式去破他们的相。",
    "因为这个师父足够厉害，所以，他可以足够自由地去演绎很多东西。可以这样理解吧？我就简单这样表达一下。",
    "众生呢，因为认证不了圆满空性。为什么认证不了？是因为他一直活在自我的喜好跟评判里面，众生是很难接纳很多东西的。所以那些比较极端的示现，他更多是接引只差临门一脚的修行人。",
    "比如说，如果有一位上师抽烟，众生马上就一定会怀疑：这个人是不是邪师？这个人怎么怎么样？",
    "但这可能是破别人修行相的示现，告诉你，你不一定非要看起来多么优雅；你不一定非要去符合众生的预期，才是一个真正的修行人；你不一定非要看起来状态很好，才能开始修行。",
    "如果我记得没错的话，应该就是邱阳创巴仁波切，他当众抽烟，他这样说：“如果我的抽烟能告诉别人，你并不一定非要等到自己有一个很好的状态的时候才能开始修行，那不也挺好的吗？”就这个意思。",
    "这样的上师示现是少数，也不能大多数。众生还是需要循规蹈矩地去修证佛法的。太多这样的极端的示现的话，会扰乱市场，会模糊众生的视线，众生会更加真假难辨，是不是？你们想想是不是？",
    "时不时偶尔示现几个，就破很多修行人的相，破很多修行人的修行相。因为有很多修行人，他到后面的阶段的时候，他所有的相都要破干净。",
    "所以大家能看到，这不也是诸佛菩萨示现的慈悲吗？众生的信仰很多时候是非常脆弱的，大家也要去观照到自己。",
    "我们信仰的应该是生命真相和终极解脱。我们要的不是感应跟境界，我们要的也不是人天福报。我们更加不要去把自己的信仰跟某些东西挂钩。",
    "比如说，如果明天佛教暴露了很多人性之恶，你会不会怀疑佛法？你会不会停止修证？你会不会怀疑生命真相？",
    "如果会，是你的问题。你搞错了。你看向的应该是生命真相跟解脱，你看向的不应该是人性跟世间的一个佛教组织，不是吗？",
    "世界没有完美的东西。你不要指望在世间找一个大同社会、成全一个大同社会，没有一点污垢。污垢是你的定义、是你的以为，是人类狭隘的认知。",
    "如果明天我穿着紧身裙、穿着黑丝袜、穿双高跟鞋，如果我染了一头红色头发去直播，他们马上就可能就会觉得我是妖魔转世，甚至会去觉得因此而对佛法失望。",
    "就众生很难从自我的喜好里面出来的。众生还是习惯分别、批判、下定义，并且把他们的信仰跟人性的期待去挂钩。",
    "所以你们就知道为什么众生很难验证解脱，会一直沉迷在幻境、幻受里面。就大家特别容易被现象影响，而不去观照到更深的层面。",
    "但要注意的是，现象只是现象，呈现只是呈现。所有的呈现都是一种示现，是一种警示和照见，是你的镜子，照见你有没有认证和回归绝对的大圆满。是不是？",
    "一切的呈现都是镜子，不是给你用来去批判的、给你去解读的、不是给你去完成自我的游戏的。是镜子，是镜子，是帮你照见你自己有没有完全认证大圆满、认证你有没有解脱、有没有从一切的现象里面出离。",
    "所有的事情和呈现，对你来讲都是镜子。不需要你的建议，不需要你的意见，不需要你去批判，不需要你自以为是的解读。如果你执着于解读跟发表意见，你就必然还在沉迷于自我的游戏，你就会迷失在幻境幻相里面。",
    "给大家增加一个角度去看看很多高僧大德的事迹，给大家多一个角度去看看高僧大德的示现，大家会看出不一样的东西。",
    "有些上师现的相，是真的非常难以被世人理解的，比如说邱阳创巴仁波切刚刚讲的。还有的上师骂人、满嘴脏话。",
    "如果你听到别人骂人，你马上就开始质疑佛法、怀疑这个人、攻击这个人，他暴露的是你的烦恼心。那他不是一个很好的镜子吗？",
    "那你当下就要明白，他为什么会这样示现？不就是为了揭露像你这样的假模假式的修行人吗？是不是？",
    "还有比如说二祖去妓院。人家为什么要去妓院？闲得慌吗？凑巧吗？是不是？不仅示现去妓院的相，还示现杀相。",
    "像僧肇大师也是，二祖也是被砍头。很多示现都是为了破一些修行人最后的执着跟着相。很多的示现，是要做出真正圆满空性的示现。虽然很多众生会不理解、看不明白，但一定有另外一些众生需要。"
  ],
  "author": "赖宽心",
  "sourceStatus": "published-source",
  "reviewStatus": "pending",
  "sourceUrl": "https://mp.weixin.qq.com/s/9fIGRm_a1ZVlmHFMlyGWfA"
}
